[
  {
    "location":"서울특별시 송파구 방이동",
    "title":"유다"
  },
  {
    "location":"서울특별시 송파구 방이동",
    "title":"메리고키친"
  },
  {
    "location":"서울특별시 송파구 방이동",
    "title":"빨간오뎅"
  },
  {
    "location":"서울특별시 송파구 방이동",
    "title":"소담 안동국시"
  },
  {
    "location":"서울특별시 송파구 방이동",
    "title":"피어오르다"
  },
  {
    "location":"서울특별시 송파구 방이동",
    "title":"하남춘천골닭갈비"
  },
  {
    "location":"서울특별시 송파구 방이동",
    "title":"신촌황소곱창"
  },
  {
    "location":"서울특별시 송파구 방이동",
    "title":"쏘아베"
  },
  {
    "location":"서울특별시 송파구 방이동",
    "title":"남도바다"
  },
  {
    "location":"서울특별시 송파구 방이동",
    "title":"뽀빠이우렁추어탕"
  },
  {
    "location":"서울특별시 송파구 방이동",
    "title":"오브모닝"
  },
  {
    "location":"서울특별시 송파구 방이동",
    "title":"서울올림픽파크텔커피숍"
  },
  {
    "location":"서울특별시 송파구 방이동",
    "title":"청춘"
  },
  {
    "location":"서울특별시 송파구 방이동",
    "title":"시즈너블베이커리"
  },
  {
    "location":"서울특별시 송파구 방이동",
    "title":"블루멘가쎄"
  },
  {
    "location":"서울특별시 송파구 방이동",
    "title":"윤화돈까스"
  },
  {
    "location":"서울특별시 송파구 방이동",
    "title":"터치183"
  },
  {
    "location":"서울특별시 송파구 방이동",
    "title":"더램"
  },
  {
    "location":"서울특별시 송파구 방이동",
    "title":"오동나무집24시감자국"
  },
  {
    "location":"서울특별시 송파구 방이동",
    "title":"방이동쭈꾸미"
  },
  {
    "location":"서울특별시 송파구 방이동",
    "title":"VOSTOK"
  },
  {
    "location":"서울특별시 송파구 방이동",
    "title":"금왕평양면옥"
  },
  {
    "location":"서울특별시 송파구 방이동",
    "title":"골든타이"
  },
  {
    "location":"서울특별시 송파구 방이동",
    "title":"을밀대"
  },
  {
    "location":"서울특별시 송파구 방이동",
    "title":"슈타인도르프"
  },
  {
    "location":"서울특별시 송파구 방이동",
    "title":"파리크라상"
  },
  {
    "location":"서울특별시 송파구 방이동",
    "title":"스시유메"
  },
  {
    "location":"서울특별시 송파구 방이동",
    "title":"트라토리아브로도"
  },
  {
    "location":"서울특별시 송파구 방이동",
    "title":"Le Sud Seoul"
  },
  {
    "location":"서울특별시 송파구 방이동",
    "title":"징기스"
  },
  {
    "location":"서울특별시 송파구 방이동",
    "title":"제로베이커리"
  },
  {
    "location":"서울특별시 송파구 방이동",
    "title":"당산오돌"
  },
  {
    "location":"서울특별시 송파구 방이동",
    "title":"벽제갈비"
  },
  {
    "location":"서울특별시 송파구 방이동",
    "title":"서울제빵소"
  },
  {
    "location":"서울특별시 송파구 방이동",
    "title":"배키욘방"
  },
  {
    "location":"서울특별시 송파구 방이동",
    "title":"코벤트가든"
  },
  {
    "location":"서울특별시 송파구 방이동",
    "title":"홍종흔베이커리"
  },
  {
    "location":"서울특별시 송파구 방이동",
    "title":"스톤앤워터"
  },
  {
    "location":"서울특별시 송파구 방이동",
    "title":"숙달돼지"
  },
  {
    "location":"서울특별시 송파구 방이동",
    "title":"홈수끼"
  },
  {
    "location":"서울특별시 송파구 방이동",
    "title":"백암왕순대"
  },
  {
    "location":"서울특별시 송파구 방이동",
    "title":"스시작"
  },
  {
    "location":"서울특별시 송파구 방이동",
    "title":"한아람정육식당"
  },
  {
    "location":"서울특별시 송파구 방이동",
    "title":"몽중헌"
  },
  {
    "location":"서울특별시 송파구 방이동",
    "title":"봉피양"
  },
  {
    "location":"서울특별시 송파구 방이동",
    "title":"니꾸바시야"
  },
  {
    "location":"서울특별시 송파구 방이동",
    "title":"스타쉐프 바이 후남"
  },
  {
    "location":"서울특별시 송파구 방이동",
    "title":"별미곱창"
  },
  {
    "location":"서울특별시 송파구 방이동",
    "title":"살롱드쥬"
  },
  {
    "location":"서울특별시 송파구 방이동",
    "title":"육화식당"
  },
  {
    "location":"서울특별시 송파구 방이동",
    "title":"가일"
  },
  {
    "location":"서울특별시 송파구 방이동",
    "title":"오키나와블루"
  },
  {
    "location":"서울특별시 송파구 방이동",
    "title":"정목누룽지백숙"
  },
  {
    "location":"서울특별시 송파구 방이동",
    "title":"조용"
  },
  {
    "location":"서울특별시 송파구 방이동",
    "title":"공룡떡볶이"
  },
  {
    "location":"서울특별시 송파구 방이동",
    "title":"서두산딤섬만두"
  },
  {
    "location":"서울특별시 송파구 방이동",
    "title":"소담정"
  },
  {
    "location":"서울특별시 송파구 방이동",
    "title":"차고버거"
  },
  {
    "location":"서울특별시 송파구 방이동",
    "title":"송계옥"
  },
  {
    "location":"서울특별시 송파구 방이동",
    "title":"방이샤브샤브칼국수"
  },
  {
    "location":"서울특별시 송파구 방이동",
    "title":"츠쿠모"
  },
  {
    "location":"서울특별시 송파구 방이동",
    "title":"등촌샤브칼국수"
  },
  {
    "location":"서울특별시 송파구 방이동",
    "title":"제주오겹살왕돌구이집"
  },
  {
    "location":"서울특별시 송파구 방이동",
    "title":"오사카하루"
  },
  {
    "location":"서울특별시 송파구 방이동",
    "title":"돈이찌"
  },
  {
    "location":"서울특별시 송파구 방이동",
    "title":"작살치킨"
  },
  {
    "location":"서울특별시 송파구 방이동",
    "title":"제일제면소"
  },
  {
    "location":"서울특별시 송파구 방이동",
    "title":"라디오헤드 펍"
  },
  {
    "location":"서울특별시 송파구 방이동",
    "title":"서두산딤섬"
  },
  {
    "location":"서울특별시 송파구 방이동",
    "title":"꼭그닭 셀프텝 하우스"
  },
  {
    "location":"서울특별시 송파구 방이동",
    "title":"크래버대게나라"
  },
  {
    "location":"서울특별시 송파구 방이동",
    "title":"삿뽀로"
  },
  {
    "location":"서울특별시 송파구 방이동",
    "title":"미우미우"
  },
  {
    "location":"서울특별시 송파구 방이동",
    "title":"gufo파스타 앤 이태리포차"
  },
  {
    "location":"서울특별시 송파구 방이동",
    "title":"마시마니"
  },
  {
    "location":"서울특별시 송파구 방이동",
    "title":"킨쇼"
  },
  {
    "location":"서울특별시 송파구 방이동",
    "title":"소류"
  },
  {
    "location":"서울특별시 송파구 방이동",
    "title":"경복궁"
  },
  {
    "location":"서울특별시 송파구 방이동",
    "title":"일월고기"
  },
  {
    "location":"서울특별시 송파구 방이동",
    "title":"농부의꿈"
  },
  {
    "location":"서울특별시 송파구 방이동",
    "title":"우직"
  },
  {
    "location":"서울특별시 송파구 방이동",
    "title":"명성곱창"
  },
  {
    "location":"서울특별시 송파구 방이동",
    "title":"신의주부대찌개"
  },
  {
    "location":"서울특별시 송파구 방이동",
    "title":"Good Vibe"
  },
  {
    "location":"서울특별시 송파구 방이동",
    "title":"로만티쿠스"
  },
  {
    "location":"서울특별시 송파구 방이동",
    "title":"회초리"
  },
  {
    "location":"서울특별시 송파구 방이동",
    "title":"연안식당"
  },
  {
    "location":"서울특별시 송파구 방이동",
    "title":"아티제"
  },
  {
    "location":"서울특별시 송파구 방이동",
    "title":"해미소참치"
  },
  {
    "location":"서울특별시 송파구 방이동",
    "title":"마포서서갈비"
  },
  {
    "location":"서울특별시 송파구 방이동",
    "title":"삿포로참치"
  },
  {
    "location":"서울특별시 송파구 방이동",
    "title":"COMMA TABLE"
  },
  {
    "location":"서울특별시 송파구 방이동",
    "title":"형제애"
  },
  {
    "location":"서울특별시 송파구 방이동",
    "title":"호호부엌"
  },
  {
    "location":"서울특별시 송파구 방이동",
    "title":"나레초밥"
  },
  {
    "location":"서울특별시 송파구 방이동",
    "title":"구이본가황포돛배"
  },
  {
    "location":"서울특별시 송파구 방이동",
    "title":"오늘도갈비"
  },
  {
    "location":"서울특별시 송파구 방이동",
    "title":"평양만두한상"
  },
  {
    "location":"서울특별시 송파구 방이동",
    "title":"피슈마라홍탕"
  },
  {
    "location":"서울특별시 송파구 방이동",
    "title":"돌마리포차"
  },
  {
    "location":"서울특별시 송파구 방이동",
    "title":"금강산감자탕"
  },
  {
    "location":"서울특별시 송파구 방이동",
    "title":"더마칸"
  },
  {
    "location":"서울특별시 송파구 방이동",
    "title":"청라언덕"
  },
  {
    "location":"서울특별시 송파구 방이동",
    "title":"참치의미"
  },
  {
    "location":"서울특별시 송파구 방이동",
    "title":"좋은생고기정육점식당"
  },
  {
    "location":"서울특별시 송파구 방이동",
    "title":"최고집손칼국수"
  },
  {
    "location":"서울특별시 송파구 방이동",
    "title":"우리강산"
  },
  {
    "location":"서울특별시 송파구 방이동",
    "title":"찌유"
  },
  {
    "location":"서울특별시 송파구 방이동",
    "title":"뽕사부"
  },
  {
    "location":"서울특별시 송파구 방이동",
    "title":"카츠젠"
  },
  {
    "location":"서울특별시 송파구 방이동",
    "title":"프레젠트"
  },
  {
    "location":"서울특별시 송파구 방이동",
    "title":"포모르"
  },
  {
    "location":"서울특별시 송파구 방이동",
    "title":"우드그린4717"
  },
  {
    "location":"서울특별시 송파구 방이동",
    "title":"콩심"
  },
  {
    "location":"서울특별시 송파구 방이동",
    "title":"더뷰이자카야"
  },
  {
    "location":"서울특별시 송파구 방이동",
    "title":"모범떡볶이1976"
  },
  {
    "location":"서울특별시 송파구 방이동",
    "title":"올가베이커리"
  },
  {
    "location":"서울특별시 송파구 방이동",
    "title":"카도식당"
  },
  {
    "location":"서울특별시 송파구 방이동",
    "title":"다랑손칼국수"
  },
  {
    "location":"서울특별시 송파구 방이동",
    "title":"바다빈치"
  },
  {
    "location":"서울특별시 송파구 방이동",
    "title":"램스가든"
  },
  {
    "location":"서울특별시 송파구 방이동",
    "title":"직화방2"
  },
  {
    "location":"서울특별시 송파구 방이동",
    "title":"담소사골순대"
  },
  {
    "location":"서울특별시 송파구 방이동",
    "title":"함초밭들깨칼국수"
  },
  {
    "location":"서울특별시 송파구 방이동",
    "title":"이찌미돈까스"
  },
  {
    "location":"서울특별시 송파구 방이동",
    "title":"원조부산화로양곱창"
  },
  {
    "location":"서울특별시 송파구 방이동",
    "title":"깍뚝연탄구이"
  },
  {
    "location":"서울특별시 송파구 방이동",
    "title":"오징어청춘"
  },
  {
    "location":"서울특별시 송파구 방이동",
    "title":"윤정주순대국"
  },
  {
    "location":"서울특별시 송파구 방이동",
    "title":"방이손칼국수"
  },
  {
    "location":"서울특별시 송파구 방이동",
    "title":"더라스트게임"
  },
  {
    "location":"서울특별시 송파구 방이동",
    "title":"우에노스시"
  },
  {
    "location":"서울특별시 송파구 방이동",
    "title":"드리퍼"
  },
  {
    "location":"서울특별시 송파구 방이동",
    "title":"자연구이가"
  },
  {
    "location":"서울특별시 송파구 방이동",
    "title":"시골보리밥&돈까스"
  },
  {
    "location":"서울특별시 송파구 방이동",
    "title":"소청도양갈비"
  },
  {
    "location":"서울특별시 송파구 방이동",
    "title":"핸드쿤스트"
  },
  {
    "location":"서울특별시 송파구 방이동",
    "title":"대독장"
  },
  {
    "location":"서울특별시 송파구 방이동",
    "title":"카모메 심야식당"
  },
  {
    "location":"서울특별시 송파구 방이동",
    "title":"깐부치킨"
  },
  {
    "location":"서울특별시 송파구 방이동",
    "title":"영동족발"
  },
  {
    "location":"서울특별시 송파구 방이동",
    "title":"한방삼계탕"
  },
  {
    "location":"서울특별시 송파구 방이동",
    "title":"밀회관"
  },
  {
    "location":"서울특별시 송파구 방이동",
    "title":"금강풍천민물장어"
  },
  {
    "location":"서울특별시 송파구 방이동",
    "title":"하얀스시"
  },
  {
    "location":"서울특별시 송파구 방이동",
    "title":"후리"
  },
  {
    "location":"서울특별시 송파구 방이동",
    "title":"카페라리"
  },
  {
    "location":"서울특별시 송파구 방이동",
    "title":"세광양대창"
  },
  {
    "location":"서울특별시 송파구 방이동",
    "title":"하남돼지집"
  },
  {
    "location":"서울특별시 송파구 방이동",
    "title":"놀부유황오리진흙구이"
  },
  {
    "location":"서울특별시 송파구 방이동",
    "title":"오븐스프링"
  },
  {
    "location":"서울특별시 송파구 방이동",
    "title":"교대이층집"
  },
  {
    "location":"서울특별시 송파구 방이동",
    "title":"레스토랑제미"
  },
  {
    "location":"서울특별시 송파구 방이동",
    "title":"연발탄"
  },
  {
    "location":"서울특별시 송파구 방이동",
    "title":"소호정"
  },
  {
    "location":"서울특별시 송파구 방이동",
    "title":"만주"
  },
  {
    "location":"서울특별시 송파구 방이동",
    "title":"미성양꼬치"
  },
  {
    "location":"서울특별시 송파구 방이동",
    "title":"이백안창구이"
  },
  {
    "location":"서울특별시 송파구 방이동",
    "title":"오륜브레드"
  },
  {
    "location":"서울특별시 송파구 방이동",
    "title":"7프로칠백식당"
  },
  {
    "location":"서울특별시 송파구 방이동",
    "title":"청년감자탕"
  },
  {
    "location":"서울특별시 송파구 방이동",
    "title":"이자카야레스펍"
  },
  {
    "location":"서울특별시 송파구 방이동",
    "title":"아이엠바리스타"
  },
  {
    "location":"서울특별시 송파구 방이동",
    "title":"빽돈"
  },
  {
    "location":"서울특별시 송파구 방이동",
    "title":"방이성"
  },
  {
    "location":"서울특별시 송파구 방이동",
    "title":"동경레스펍"
  },
  {
    "location":"서울특별시 송파구 방이동",
    "title":"홉쏘"
  },
  {
    "location":"서울특별시 송파구 방이동",
    "title":"단골손님"
  },
  {
    "location":"서울특별시 송파구 방이동",
    "title":"인기명"
  },
  {
    "location":"서울특별시 송파구 방이동",
    "title":"방이골목떡볶이"
  },
  {
    "location":"서울특별시 송파구 방이동",
    "title":"일로스페인"
  },
  {
    "location":"서울특별시 송파구 방이동",
    "title":"식도원"
  },
  {
    "location":"서울특별시 송파구 방이동",
    "title":"생 클레어"
  },
  {
    "location":"서울특별시 송파구 방이동",
    "title":"대성연탄갈비"
  },
  {
    "location":"서울특별시 송파구 방이동",
    "title":"코코라운지"
  },
  {
    "location":"서울특별시 송파구 방이동",
    "title":"미나미"
  },
  {
    "location":"서울특별시 송파구 방이동",
    "title":"가원"
  },
  {
    "location":"서울특별시 송파구 방이동",
    "title":"강원도청국장"
  },
  {
    "location":"서울특별시 송파구 방이동",
    "title":"다다풀코스일식"
  },
  {
    "location":"서울특별시 송파구 방이동",
    "title":"동네형아"
  },
  {
    "location":"서울특별시 송파구 방이동",
    "title":"빌러브드 티카페"
  },
  {
    "location":"서울특별시 송파구 방이동",
    "title":"로지스시"
  },
  {
    "location":"서울특별시 송파구 방이동",
    "title":"송파생태전문점"
  },
  {
    "location":"서울특별시 송파구 방이동",
    "title":"옐로우샤크"
  },
  {
    "location":"서울특별시 송파구 방이동",
    "title":"항방양꼬치"
  },
  {
    "location":"서울특별시 송파구 방이동",
    "title":"명가원설농탕"
  },
  {
    "location":"서울특별시 송파구 방이동",
    "title":"동봉커피"
  },
  {
    "location":"서울특별시 송파구 방이동",
    "title":"제주항"
  },
  {
    "location":"서울특별시 송파구 방이동",
    "title":"제주곳간"
  },
  {
    "location":"서울특별시 송파구 방이동",
    "title":"죽변항"
  },
  {
    "location":"서울특별시 송파구 방이동",
    "title":"엉터리생고기"
  },
  {
    "location":"서울특별시 송파구 방이동",
    "title":"착한우정육식당"
  },
  {
    "location":"서울특별시 송파구 방이동",
    "title":"펀비어킹"
  },
  {
    "location":"서울특별시 송파구 방이동",
    "title":"이레"
  },
  {
    "location":"서울특별시 송파구 방이동",
    "title":"조은분식"
  },
  {
    "location":"서울특별시 송파구 방이동",
    "title":"한우한마리"
  },
  {
    "location":"서울특별시 송파구 방이동",
    "title":"우리네식당"
  },
  {
    "location":"서울특별시 송파구 방이동",
    "title":"포지타노"
  },
  {
    "location":"서울특별시 송파구 방이동",
    "title":"가장맛있는족발"
  },
  {
    "location":"서울특별시 송파구 방이동",
    "title":"커피빈"
  },
  {
    "location":"서울특별시 송파구 방이동",
    "title":"외쿸부엌"
  },
  {
    "location":"서울특별시 송파구 방이동",
    "title":"통영멸치국수"
  },
  {
    "location":"서울특별시 송파구 방이동",
    "title":"용호동낙지"
  },
  {
    "location":"서울특별시 송파구 방이동",
    "title":"일출항"
  },
  {
    "location":"서울특별시 송파구 방이동",
    "title":"오늘국밥과우동"
  },
  {
    "location":"서울특별시 송파구 방이동",
    "title":"커피빈"
  },
  {
    "location":"서울특별시 송파구 방이동",
    "title":"내고향횡성한우정육점식당"
  },
  {
    "location":"서울특별시 송파구 방이동",
    "title":"삐에로와인펍"
  },
  {
    "location":"서울특별시 송파구 방이동",
    "title":"해닭"
  },
  {
    "location":"서울특별시 송파구 방이동",
    "title":"카페미뇽"
  },
  {
    "location":"서울특별시 송파구 방이동",
    "title":"이자카야 오모"
  },
  {
    "location":"서울특별시 송파구 방이동",
    "title":"니나니노카페"
  },
  {
    "location":"서울특별시 송파구 방이동",
    "title":"웰컴투세맛골"
  },
  {
    "location":"서울특별시 송파구 방이동",
    "title":"푸미흥"
  },
  {
    "location":"서울특별시 송파구 방이동",
    "title":"화이트웨일"
  },
  {
    "location":"서울특별시 송파구 방이동",
    "title":"골든커피"
  },
  {
    "location":"서울특별시 송파구 방이동",
    "title":"1987루프탑라운지"
  },
  {
    "location":"서울특별시 송파구 방이동",
    "title":"현차이나"
  },
  {
    "location":"서울특별시 송파구 방이동",
    "title":"평이담백 뼈칼국수"
  },
  {
    "location":"서울특별시 송파구 방이동",
    "title":"원조왕십리곱창"
  },
  {
    "location":"서울특별시 송파구 방이동",
    "title":"이백"
  },
  {
    "location":"서울특별시 송파구 방이동",
    "title":"옛촌매운갈비찜"
  },
  {
    "location":"서울특별시 송파구 방이동",
    "title":"포유티"
  },
  {
    "location":"서울특별시 송파구 방이동",
    "title":"연형"
  },
  {
    "location":"서울특별시 송파구 방이동",
    "title":"명불허전원조골뱅이"
  },
  {
    "location":"서울특별시 송파구 방이동",
    "title":"전국낙지자랑"
  },
  {
    "location":"서울특별시 송파구 방이동",
    "title":"진성한우곱창"
  },
  {
    "location":"서울특별시 송파구 방이동",
    "title":"맛있는칼국수"
  },
  {
    "location":"서울특별시 송파구 방이동",
    "title":"부산아지매국밥"
  },
  {
    "location":"서울특별시 송파구 방이동",
    "title":"퀸즈가든"
  },
  {
    "location":"서울특별시 송파구 방이동",
    "title":"와타미"
  },
  {
    "location":"서울특별시 송파구 방이동",
    "title":"예쁜소나무"
  },
  {
    "location":"서울특별시 송파구 방이동",
    "title":"청담초밥"
  },
  {
    "location":"서울특별시 송파구 방이동",
    "title":"미오"
  },
  {
    "location":"서울특별시 송파구 방이동",
    "title":"마왕족발"
  },
  {
    "location":"서울특별시 송파구 방이동",
    "title":"두리닭발"
  },
  {
    "location":"서울특별시 송파구 방이동",
    "title":"우버금"
  },
  {
    "location":"서울특별시 송파구 방이동",
    "title":"오니샐러드"
  },
  {
    "location":"서울특별시 송파구 방이동",
    "title":"진이찬방"
  },
  {
    "location":"서울특별시 송파구 방이동",
    "title":"스시미노루"
  },
  {
    "location":"서울특별시 송파구 방이동",
    "title":"서울김밥"
  },
  {
    "location":"서울특별시 송파구 방이동",
    "title":"동대문닭한마리"
  },
  {
    "location":"서울특별시 송파구 방이동",
    "title":"밀향기해물손칼국수"
  },
  {
    "location":"서울특별시 송파구 방이동",
    "title":"영춘똥꼬닭발"
  },
  {
    "location":"서울특별시 송파구 방이동",
    "title":"24시통큰찌개집"
  },
  {
    "location":"서울특별시 송파구 방이동",
    "title":"산카이"
  },
  {
    "location":"서울특별시 송파구 방이동",
    "title":"코이라멘"
  },
  {
    "location":"서울특별시 송파구 방이동",
    "title":"난랑"
  },
  {
    "location":"서울특별시 송파구 방이동",
    "title":"맘스터치"
  },
  {
    "location":"서울특별시 송파구 방이동",
    "title":"군산아구꽃게전문점"
  },
  {
    "location":"서울특별시 송파구 방이동",
    "title":"정원양꼬치"
  },
  {
    "location":"서울특별시 송파구 방이동",
    "title":"혜화시장"
  },
  {
    "location":"서울특별시 송파구 방이동",
    "title":"오고보"
  },
  {
    "location":"서울특별시 송파구 방이동",
    "title":"잠실숯불갈비"
  },
  {
    "location":"서울특별시 송파구 방이동",
    "title":"한벽루전주콩나물국밥"
  },
  {
    "location":"서울특별시 송파구 방이동",
    "title":"바다풍경"
  },
  {
    "location":"서울특별시 송파구 방이동",
    "title":"셰프의부엌"
  },
  {
    "location":"서울특별시 송파구 방이동",
    "title":"말자싸롱"
  },
  {
    "location":"서울특별시 송파구 방이동",
    "title":"양철통"
  },
  {
    "location":"서울특별시 송파구 방이동",
    "title":"설악골추어탕"
  },
  {
    "location":"서울특별시 송파구 방이동",
    "title":"장군보쌈"
  },
  {
    "location":"서울특별시 송파구 방이동",
    "title":"돗오름"
  },
  {
    "location":"서울특별시 송파구 방이동",
    "title":"돈탐라제주냉삼1977"
  },
  {
    "location":"서울특별시 송파구 방이동",
    "title":"Volt32"
  },
  {
    "location":"서울특별시 송파구 방이동",
    "title":"양휘당"
  },
  {
    "location":"서울특별시 송파구 방이동",
    "title":"카페아이린"
  },
  {
    "location":"서울특별시 송파구 방이동",
    "title":"위치"
  },
  {
    "location":"서울특별시 송파구 방이동",
    "title":"루이스"
  },
  {
    "location":"서울특별시 송파구 방이동",
    "title":"리웨이커피"
  },
  {
    "location":"서울특별시 송파구 방이동",
    "title":"방이 능이버섯 백숙 삼계탕"
  },
  {
    "location":"서울특별시 송파구 방이동",
    "title":"한스"
  },
  {
    "location":"서울특별시 송파구 방이동",
    "title":"부부김밥"
  },
  {
    "location":"서울특별시 송파구 방이동",
    "title":"호치킨"
  },
  {
    "location":"서울특별시 송파구 방이동",
    "title":"연탄이야기"
  },
  {
    "location":"서울특별시 송파구 방이동",
    "title":"콩낙촌"
  },
  {
    "location":"서울특별시 송파구 방이동",
    "title":"해림식당"
  },
  {
    "location":"서울특별시 송파구 방이동",
    "title":"새우공방"
  },
  {
    "location":"서울특별시 송파구 방이동",
    "title":"신센"
  },
  {
    "location":"서울특별시 송파구 방이동",
    "title":"평창갈비"
  },
  {
    "location":"서울특별시 송파구 방이동",
    "title":"몬스타쉐프의사사곱창"
  },
  {
    "location":"서울특별시 송파구 방이동",
    "title":"미소울생고기"
  },
  {
    "location":"서울특별시 송파구 방이동",
    "title":"79대포"
  },
  {
    "location":"서울특별시 송파구 방이동",
    "title":"화려한수다"
  },
  {
    "location":"서울특별시 송파구 방이동",
    "title":"브롱스"
  },
  {
    "location":"서울특별시 송파구 방이동",
    "title":"돌배기집"
  },
  {
    "location":"서울특별시 송파구 방이동",
    "title":"이화수전통육개장"
  },
  {
    "location":"서울특별시 송파구 방이동",
    "title":"방산바지락칼국수"
  },
  {
    "location":"서울특별시 송파구 방이동",
    "title":"혼참치"
  },
  {
    "location":"서울특별시 송파구 방이동",
    "title":"포하이퐁"
  },
  {
    "location":"서울특별시 송파구 방이동",
    "title":"크레이지초코"
  },
  {
    "location":"서울특별시 송파구 방이동",
    "title":"주나규"
  },
  {
    "location":"서울특별시 송파구 방이동",
    "title":"홍콩반점0410"
  },
  {
    "location":"서울특별시 송파구 방이동",
    "title":"노즈"
  },
  {
    "location":"서울특별시 송파구 방이동",
    "title":"신단설렁탕"
  },
  {
    "location":"서울특별시 송파구 방이동",
    "title":"군자대한곱창"
  },
  {
    "location":"서울특별시 송파구 방이동",
    "title":"싱싱오징어바다"
  },
  {
    "location":"서울특별시 송파구 방이동",
    "title":"대즐커피"
  },
  {
    "location":"서울특별시 송파구 방이동",
    "title":"와포바인"
  },
  {
    "location":"서울특별시 송파구 방이동",
    "title":"온수반"
  },
  {
    "location":"서울특별시 송파구 방이동",
    "title":"켄지"
  },
  {
    "location":"서울특별시 송파구 방이동",
    "title":"상구비어"
  },
  {
    "location":"서울특별시 송파구 방이동",
    "title":"호치킨"
  },
  {
    "location":"서울특별시 송파구 방이동",
    "title":"곱창고"
  },
  {
    "location":"서울특별시 송파구 방이동",
    "title":"서울김밥"
  },
  {
    "location":"서울특별시 송파구 방이동",
    "title":"문어세상해천탕"
  },
  {
    "location":"서울특별시 송파구 방이동",
    "title":"매운대"
  },
  {
    "location":"서울특별시 송파구 방이동",
    "title":"프랭크서울"
  },
  {
    "location":"서울특별시 송파구 방이동",
    "title":"지금보고싶다"
  },
  {
    "location":"서울특별시 송파구 방이동",
    "title":"풍천민물장어"
  },
  {
    "location":"서울특별시 송파구 방이동",
    "title":"밤도깨비"
  },
  {
    "location":"서울특별시 송파구 방이동",
    "title":"빈체로"
  },
  {
    "location":"서울특별시 송파구 방이동",
    "title":"방이옥"
  },
  {
    "location":"서울특별시 송파구 방이동",
    "title":"공차"
  },
  {
    "location":"서울특별시 송파구 방이동",
    "title":"하선재간장게장"
  },
  {
    "location":"서울특별시 송파구 방이동",
    "title":"커피베이"
  },
  {
    "location":"서울특별시 송파구 방이동",
    "title":"전주콩나루콩나물국밥"
  },
  {
    "location":"서울특별시 송파구 방이동",
    "title":"이레우렁쌈밥"
  },
  {
    "location":"서울특별시 송파구 방이동",
    "title":"뮤직클래스"
  },
  {
    "location":"서울특별시 송파구 방이동",
    "title":"삼삼이네"
  },
  {
    "location":"서울특별시 송파구 방이동",
    "title":"키친오브인디아"
  },
  {
    "location":"서울특별시 송파구 방이동",
    "title":"성민양꼬치"
  },
  {
    "location":"서울특별시 송파구 방이동",
    "title":"마틴"
  },
  {
    "location":"서울특별시 송파구 방이동",
    "title":"해사랑"
  },
  {
    "location":"서울특별시 송파구 방이동",
    "title":"차이나타운"
  },
  {
    "location":"서울특별시 송파구 방이동",
    "title":"리더스푸드"
  },
  {
    "location":"서울특별시 송파구 방이동",
    "title":"유메"
  },
  {
    "location":"서울특별시 송파구 방이동",
    "title":"7번가피자"
  },
  {
    "location":"서울특별시 송파구 방이동",
    "title":"미가도시락"
  },
  {
    "location":"서울특별시 송파구 방이동",
    "title":"가나자와"
  },
  {
    "location":"서울특별시 송파구 방이동",
    "title":"오륜명동칼국수"
  },
  {
    "location":"서울특별시 송파구 방이동",
    "title":"또바호프"
  },
  {
    "location":"서울특별시 송파구 방이동",
    "title":"여의도떡방앗간"
  },
  {
    "location":"서울특별시 송파구 방이동",
    "title":"밀러타임"
  },
  {
    "location":"서울특별시 송파구 방이동",
    "title":"친절떡방"
  },
  {
    "location":"서울특별시 송파구 방이동",
    "title":"본죽"
  },
  {
    "location":"서울특별시 송파구 방이동",
    "title":"도연떡방"
  },
  {
    "location":"서울특별시 송파구 방이동",
    "title":"엠엔제이퓨어"
  },
  {
    "location":"서울특별시 송파구 방이동",
    "title":"닭발인생송파"
  },
  {
    "location":"서울특별시 송파구 방이동",
    "title":"도피오"
  },
  {
    "location":"서울특별시 송파구 방이동",
    "title":"홍콩"
  },
  {
    "location":"서울특별시 송파구 방이동",
    "title":"카페소피아"
  },
  {
    "location":"서울특별시 송파구 방이동",
    "title":"파리바게뜨"
  },
  {
    "location":"서울특별시 송파구 방이동",
    "title":"카페로드"
  },
  {
    "location":"서울특별시 송파구 방이동",
    "title":"전주콩나물황태국"
  },
  {
    "location":"서울특별시 송파구 방이동",
    "title":"본죽"
  },
  {
    "location":"서울특별시 송파구 방이동",
    "title":"갑순이보신탕"
  },
  {
    "location":"서울특별시 송파구 방이동",
    "title":"치킨뱅이"
  },
  {
    "location":"서울특별시 송파구 방이동",
    "title":"알앤비"
  },
  {
    "location":"서울특별시 송파구 방이동",
    "title":"잇츠커피"
  },
  {
    "location":"서울특별시 송파구 방이동",
    "title":"골든커피로스터스"
  },
  {
    "location":"서울특별시 송파구 방이동",
    "title":"참치한마리"
  },
  {
    "location":"서울특별시 송파구 방이동",
    "title":"코코루시아"
  },
  {
    "location":"서울특별시 송파구 방이동",
    "title":"열무밭"
  },
  {
    "location":"서울특별시 송파구 방이동",
    "title":"조우"
  },
  {
    "location":"서울특별시 송파구 방이동",
    "title":"일층커피바"
  },
  {
    "location":"서울특별시 송파구 방이동",
    "title":"크래프트비어타운"
  },
  {
    "location":"서울특별시 송파구 방이동",
    "title":"칸지고고"
  },
  {
    "location":"서울특별시 송파구 방이동",
    "title":"건풍치킨"
  },
  {
    "location":"서울특별시 송파구 방이동",
    "title":"홍콩반점0410"
  },
  {
    "location":"서울특별시 송파구 방이동",
    "title":"요리명가"
  },
  {
    "location":"서울특별시 송파구 방이동",
    "title":"청년다방"
  },
  {
    "location":"서울특별시 송파구 방이동",
    "title":"사이구이"
  },
  {
    "location":"서울특별시 송파구 방이동",
    "title":"송이네분식"
  },
  {
    "location":"서울특별시 송파구 방이동",
    "title":"맥주창고"
  },
  {
    "location":"서울특별시 송파구 방이동",
    "title":"동대문엽기떡볶이"
  },
  {
    "location":"서울특별시 송파구 방이동",
    "title":"애니브케이크"
  },
  {
    "location":"서울특별시 송파구 방이동",
    "title":"이디야커피"
  },
  {
    "location":"서울특별시 송파구 방이동",
    "title":"제주통돼지마을"
  },
  {
    "location":"서울특별시 송파구 방이동",
    "title":"신차이나"
  },
  {
    "location":"서울특별시 송파구 방이동",
    "title":"연과맛빈대떡"
  },
  {
    "location":"서울특별시 송파구 방이동",
    "title":"신원오리장작구이"
  },
  {
    "location":"서울특별시 송파구 방이동",
    "title":"티에스에프엔씨"
  },
  {
    "location":"서울특별시 송파구 방이동",
    "title":"경성주막1929"
  },
  {
    "location":"서울특별시 송파구 방이동",
    "title":"봉쥬르와인살롱"
  },
  {
    "location":"서울특별시 송파구 방이동",
    "title":"경복궁삼계탕"
  },
  {
    "location":"서울특별시 송파구 방이동",
    "title":"뉴욕야시장"
  },
  {
    "location":"서울특별시 송파구 방이동",
    "title":"설레임"
  },
  {
    "location":"서울특별시 송파구 방이동",
    "title":"부자등심"
  },
  {
    "location":"서울특별시 송파구 방이동",
    "title":"cafe135"
  },
  {
    "location":"서울특별시 송파구 방이동",
    "title":"구옥천생태"
  },
  {
    "location":"서울특별시 송파구 방이동",
    "title":"오늘은 생선구이"
  },
  {
    "location":"서울특별시 송파구 방이동",
    "title":"수산항"
  },
  {
    "location":"서울특별시 송파구 방이동",
    "title":"소문난갈비"
  },
  {
    "location":"서울특별시 송파구 방이동",
    "title":"이자카야 하나미"
  },
  {
    "location":"서울특별시 송파구 방이동",
    "title":"올림픽중화요리"
  },
  {
    "location":"서울특별시 송파구 방이동",
    "title":"골드5도씨맥주창고"
  },
  {
    "location":"서울특별시 송파구 방이동",
    "title":"투비"
  },
  {
    "location":"서울특별시 송파구 방이동",
    "title":"란참치"
  },
  {
    "location":"서울특별시 송파구 방이동",
    "title":"보부상감자탕"
  },
  {
    "location":"서울특별시 송파구 방이동",
    "title":"다감"
  },
  {
    "location":"서울특별시 송파구 방이동",
    "title":"소양집"
  },
  {
    "location":"서울특별시 송파구 방이동",
    "title":"토크쇼"
  },
  {
    "location":"서울특별시 송파구 방이동",
    "title":"피자알볼로"
  },
  {
    "location":"서울특별시 송파구 방이동",
    "title":"김밥마을"
  },
  {
    "location":"서울특별시 송파구 방이동",
    "title":"더블유바"
  },
  {
    "location":"서울특별시 송파구 방이동",
    "title":"박대박조개찜"
  },
  {
    "location":"서울특별시 송파구 방이동",
    "title":"맛자랑전통순댓국"
  },
  {
    "location":"서울특별시 송파구 방이동",
    "title":"커피빈"
  },
  {
    "location":"서울특별시 송파구 방이동",
    "title":"청류면옥"
  },
  {
    "location":"서울특별시 송파구 방이동",
    "title":"춘향고을"
  },
  {
    "location":"서울특별시 송파구 방이동",
    "title":"황토골"
  },
  {
    "location":"서울특별시 송파구 방이동",
    "title":"자율한식뷔페"
  },
  {
    "location":"서울특별시 송파구 방이동",
    "title":"명동칼국수샤브샤브"
  },
  {
    "location":"서울특별시 송파구 방이동",
    "title":"서장금불고기"
  },
  {
    "location":"서울특별시 송파구 방이동",
    "title":"보배반점"
  },
  {
    "location":"서울특별시 송파구 방이동",
    "title":"빕스"
  },
  {
    "location":"서울특별시 송파구 방이동",
    "title":"치맥"
  },
  {
    "location":"서울특별시 송파구 방이동",
    "title":"꿀미소"
  },
  {
    "location":"서울특별시 송파구 방이동",
    "title":"쭈꾸미도사"
  },
  {
    "location":"서울특별시 송파구 방이동",
    "title":"카페 보우"
  },
  {
    "location":"서울특별시 송파구 방이동",
    "title":"베이크베이직"
  },
  {
    "location":"서울특별시 송파구 방이동",
    "title":"제주하우스"
  },
  {
    "location":"서울특별시 송파구 방이동",
    "title":"도람"
  },
  {
    "location":"서울특별시 송파구 방이동",
    "title":"풍원"
  },
  {
    "location":"서울특별시 송파구 방이동",
    "title":"동대구탕"
  },
  {
    "location":"서울특별시 송파구 방이동",
    "title":"봉구비어"
  },
  {
    "location":"서울특별시 송파구 방이동",
    "title":"사람사는 고깃집 김일도"
  },
  {
    "location":"서울특별시 송파구 방이동",
    "title":"북경원"
  },
  {
    "location":"서울특별시 송파구 방이동",
    "title":"기꾸참치"
  },
  {
    "location":"서울특별시 송파구 방이동",
    "title":"보스골뱅이치킨"
  },
  {
    "location":"서울특별시 송파구 방이동",
    "title":"코리안숯불닭바베큐"
  },
  {
    "location":"서울특별시 송파구 방이동",
    "title":"미소야"
  },
  {
    "location":"서울특별시 송파구 방이동",
    "title":"레드제플린"
  },
  {
    "location":"서울특별시 송파구 방이동",
    "title":"한양순대해장국"
  },
  {
    "location":"서울특별시 송파구 방이동",
    "title":"태"
  },
  {
    "location":"서울특별시 송파구 방이동",
    "title":"난향"
  },
  {
    "location":"서울특별시 송파구 방이동",
    "title":"단풍애김밥"
  },
  {
    "location":"서울특별시 송파구 방이동",
    "title":"올림픽양곱창"
  },
  {
    "location":"서울특별시 송파구 방이동",
    "title":"중국요리북경"
  },
  {
    "location":"서울특별시 송파구 방이동",
    "title":"행복한칼국수"
  },
  {
    "location":"서울특별시 송파구 방이동",
    "title":"장인미역"
  },
  {
    "location":"서울특별시 송파구 방이동",
    "title":"마마곱창"
  },
  {
    "location":"서울특별시 송파구 방이동",
    "title":"청 치킨"
  },
  {
    "location":"서울특별시 송파구 방이동",
    "title":"병천순대국"
  },
  {
    "location":"서울특별시 송파구 방이동",
    "title":"BHC치킨"
  },
  {
    "location":"서울특별시 송파구 방이동",
    "title":"해골피자"
  },
  {
    "location":"서울특별시 송파구 방이동",
    "title":"Cafe318"
  },
  {
    "location":"서울특별시 송파구 방이동",
    "title":"동보성"
  },
  {
    "location":"서울특별시 송파구 방이동",
    "title":"일차돌"
  },
  {
    "location":"서울특별시 송파구 방이동",
    "title":"참치려"
  },
  {
    "location":"서울특별시 송파구 방이동",
    "title":"사나운치킨"
  },
  {
    "location":"서울특별시 송파구 방이동",
    "title":"SOOTTI"
  },
  {
    "location":"서울특별시 송파구 방이동",
    "title":"포메인"
  },
  {
    "location":"서울특별시 송파구 방이동",
    "title":"디이알커피"
  },
  {
    "location":"서울특별시 송파구 방이동",
    "title":"이카리"
  },
  {
    "location":"서울특별시 송파구 방이동",
    "title":"시부야카츠"
  },
  {
    "location":"서울특별시 송파구 방이동",
    "title":"한국계"
  },
  {
    "location":"서울특별시 송파구 방이동",
    "title":"오하나"
  },
  {
    "location":"서울특별시 송파구 방이동",
    "title":"카페 바운더리프리"
  },
  {
    "location":"서울특별시 송파구 방이동",
    "title":"소담히"
  },
  {
    "location":"서울특별시 송파구 방이동",
    "title":"온나우커피"
  },
  {
    "location":"서울특별시 송파구 방이동",
    "title":"청년고기장수"
  },
  {
    "location":"서울특별시 송파구 방이동",
    "title":"스타벅스"
  },
  {
    "location":"서울특별시 송파구 방이동",
    "title":"백제오뎅"
  },
  {
    "location":"서울특별시 송파구 방이동",
    "title":"디제르뷔"
  },
  {
    "location":"서울특별시 송파구 방이동",
    "title":"우정국"
  },
  {
    "location":"서울특별시 송파구 방이동",
    "title":"버터바"
  },
  {
    "location":"서울특별시 송파구 방이동",
    "title":"앤선커피"
  },
  {
    "location":"서울특별시 송파구 방이동",
    "title":"소양식탁"
  },
  {
    "location":"서울특별시 송파구 방이동",
    "title":"몽보홍"
  },
  {
    "location":"서울특별시 송파구 방이동",
    "title":"우지커피"
  },
  {
    "location":"서울특별시 송파구 방이동",
    "title":"카페알로하포롱"
  },
  {
    "location":"서울특별시 송파구 방이동",
    "title":"장우족발"
  },
  {
    "location":"서울특별시 송파구 방이동",
    "title":"옛날농장"
  },
  {
    "location":"서울특별시 송파구 방이동",
    "title":"우돈골"
  },
  {
    "location":"서울특별시 송파구 방이동",
    "title":"보사노바 커피로스터스"
  },
  {
    "location":"서울특별시 송파구 방이동",
    "title":"24시투가리해장국"
  },
  {
    "location":"서울특별시 송파구 방이동",
    "title":"꼬쟁이"
  },
  {
    "location":"서울특별시 송파구 방이동",
    "title":"보르도세계주류백화점"
  },
  {
    "location":"서울특별시 송파구 방이동",
    "title":"람세스"
  },
  {
    "location":"서울특별시 송파구 방이동",
    "title":"동가도시락"
  },
  {
    "location":"서울특별시 송파구 방이동",
    "title":"페퍼런치"
  },
  {
    "location":"서울특별시 송파구 방이동",
    "title":"빈방"
  },
  {
    "location":"서울특별시 송파구 방이동",
    "title":"올림픽떡집"
  },
  {
    "location":"서울특별시 송파구 방이동",
    "title":"피자헤븐"
  },
  {
    "location":"서울특별시 송파구 방이동",
    "title":"엄마손반찬"
  },
  {
    "location":"서울특별시 송파구 방이동",
    "title":"개성집"
  },
  {
    "location":"서울특별시 송파구 방이동",
    "title":"오시리또오시리"
  },
  {
    "location":"서울특별시 송파구 방이동",
    "title":"예당떡방"
  },
  {
    "location":"서울특별시 송파구 방이동",
    "title":"비어폭스"
  },
  {
    "location":"서울특별시 송파구 방이동",
    "title":"백제보리밥부페"
  },
  {
    "location":"서울특별시 송파구 방이동",
    "title":"맘마킹도시락올림픽공원"
  },
  {
    "location":"서울특별시 송파구 방이동",
    "title":"클레어파티세리"
  },
  {
    "location":"서울특별시 송파구 방이동",
    "title":"황태마당"
  },
  {
    "location":"서울특별시 송파구 방이동",
    "title":"보국양갈비"
  },
  {
    "location":"서울특별시 송파구 방이동",
    "title":"별별성격카페"
  },
  {
    "location":"서울특별시 송파구 방이동",
    "title":"뼈찜대감자탕"
  },
  {
    "location":"서울특별시 송파구 방이동",
    "title":"고반식당"
  },
  {
    "location":"서울특별시 송파구 방이동",
    "title":"탐라포차"
  },
  {
    "location":"서울특별시 송파구 방이동",
    "title":"또래오래"
  },
  {
    "location":"서울특별시 송파구 방이동",
    "title":"이상스시"
  },
  {
    "location":"서울특별시 송파구 방이동",
    "title":"폴앤폴리나"
  },
  {
    "location":"서울특별시 송파구 방이동",
    "title":"을지골뱅이"
  },
  {
    "location":"서울특별시 송파구 방이동",
    "title":"투썸플레이스"
  },
  {
    "location":"서울특별시 송파구 방이동",
    "title":"뚜껍집1984"
  },
  {
    "location":"서울특별시 송파구 방이동",
    "title":"삼멘카페"
  },
  {
    "location":"서울특별시 송파구 방이동",
    "title":"원조감자탕"
  },
  {
    "location":"서울특별시 송파구 방이동",
    "title":"커피숍앤레스토랑"
  },
  {
    "location":"서울특별시 송파구 방이동",
    "title":"장생관"
  },
  {
    "location":"서울특별시 송파구 방이동",
    "title":"이차돌"
  },
  {
    "location":"서울특별시 송파구 방이동",
    "title":"닥터검프"
  },
  {
    "location":"서울특별시 송파구 방이동",
    "title":"히엘로스터리카페"
  },
  {
    "location":"서울특별시 송파구 방이동",
    "title":"혼디커피"
  },
  {
    "location":"서울특별시 송파구 방이동",
    "title":"해랑"
  },
  {
    "location":"서울특별시 송파구 방이동",
    "title":"놀부부대찌개&철판구이"
  },
  {
    "location":"서울특별시 송파구 방이동",
    "title":"옛날삼겹살5900"
  },
  {
    "location":"서울특별시 송파구 방이동",
    "title":"이어도횟집"
  },
  {
    "location":"서울특별시 송파구 방이동",
    "title":"가장맛있는족발"
  },
  {
    "location":"서울특별시 송파구 방이동",
    "title":"블루바"
  },
  {
    "location":"서울특별시 송파구 방이동",
    "title":"마더"
  },
  {
    "location":"서울특별시 송파구 방이동",
    "title":"레츠꼬꼬"
  },
  {
    "location":"서울특별시 송파구 방이동",
    "title":"도깨비마을"
  },
  {
    "location":"서울특별시 송파구 방이동",
    "title":"대박집"
  },
  {
    "location":"서울특별시 송파구 방이동",
    "title":"카페 그랜드볼룸"
  },
  {
    "location":"서울특별시 송파구 방이동",
    "title":"도르만스코리아"
  },
  {
    "location":"서울특별시 송파구 방이동",
    "title":"안흥돈까스"
  },
  {
    "location":"서울특별시 송파구 방이동",
    "title":"큰바다활어"
  },
  {
    "location":"서울특별시 송파구 방이동",
    "title":"빛나는바다"
  },
  {
    "location":"서울특별시 송파구 방이동",
    "title":"윤가네오리구이"
  },
  {
    "location":"서울특별시 송파구 방이동",
    "title":"넬쿠오레델카페"
  },
  {
    "location":"서울특별시 송파구 방이동",
    "title":"백채김치찌개"
  },
  {
    "location":"서울특별시 송파구 방이동",
    "title":"쪽갤러리"
  },
  {
    "location":"서울특별시 송파구 방이동",
    "title":"동경야시장"
  },
  {
    "location":"서울특별시 송파구 방이동",
    "title":"바티칸"
  },
  {
    "location":"서울특별시 송파구 방이동",
    "title":"별미양꼬치"
  },
  {
    "location":"서울특별시 송파구 방이동",
    "title":"한탕양푼이찌개"
  },
  {
    "location":"서울특별시 송파구 방이동",
    "title":"해초120"
  },
  {
    "location":"서울특별시 송파구 방이동",
    "title":"못난감자앤치킨"
  },
  {
    "location":"서울특별시 송파구 방이동",
    "title":"꼬치집"
  },
  {
    "location":"서울특별시 송파구 방이동",
    "title":"옛맛참숯소갈비"
  },
  {
    "location":"서울특별시 송파구 방이동",
    "title":"후라이드데이"
  },
  {
    "location":"서울특별시 송파구 방이동",
    "title":"비스 생클레어"
  },
  {
    "location":"서울특별시 송파구 방이동",
    "title":"맛집"
  },
  {
    "location":"서울특별시 송파구 방이동",
    "title":"뚱보집"
  },
  {
    "location":"서울특별시 송파구 방이동",
    "title":"밥장인"
  },
  {
    "location":"서울특별시 송파구 방이동",
    "title":"마징가퓨전주점"
  },
  {
    "location":"서울특별시 송파구 방이동",
    "title":"박지윤 생고기"
  },
  {
    "location":"서울특별시 송파구 방이동",
    "title":"비치바이브"
  },
  {
    "location":"서울특별시 송파구 방이동",
    "title":"새마을포차"
  },
  {
    "location":"서울특별시 송파구 방이동",
    "title":"송천면옥"
  },
  {
    "location":"서울특별시 송파구 방이동",
    "title":"고향삼합"
  },
  {
    "location":"서울특별시 송파구 방이동",
    "title":"카가야키키친"
  },
  {
    "location":"서울특별시 송파구 방이동",
    "title":"딱정벌레"
  },
  {
    "location":"서울특별시 송파구 방이동",
    "title":"하이뮤직타운"
  },
  {
    "location":"서울특별시 송파구 방이동",
    "title":"무쇠벼루생삼겹살"
  },
  {
    "location":"서울특별시 송파구 방이동",
    "title":"스타벅스"
  },
  {
    "location":"서울특별시 송파구 방이동",
    "title":"명조커피앤베이커리"
  },
  {
    "location":"서울특별시 송파구 방이동",
    "title":"왕돌포차왕돌소곱창"
  },
  {
    "location":"서울특별시 송파구 방이동",
    "title":"통"
  },
  {
    "location":"서울특별시 송파구 방이동",
    "title":"국민왕족발"
  },
  {
    "location":"서울특별시 송파구 방이동",
    "title":"신의주부대찌개"
  },
  {
    "location":"서울특별시 송파구 방이동",
    "title":"화반"
  },
  {
    "location":"서울특별시 송파구 방이동",
    "title":"원조장충왕족발"
  },
  {
    "location":"서울특별시 송파구 방이동",
    "title":"아미고"
  },
  {
    "location":"서울특별시 송파구 방이동",
    "title":"더베니스"
  },
  {
    "location":"서울특별시 송파구 방이동",
    "title":"장수갈비"
  },
  {
    "location":"서울특별시 송파구 방이동",
    "title":"사쿠사쿠"
  },
  {
    "location":"서울특별시 송파구 방이동",
    "title":"후루츠디"
  },
  {
    "location":"서울특별시 송파구 방이동",
    "title":"꽃마름"
  },
  {
    "location":"서울특별시 송파구 방이동",
    "title":"논두렁황소곱창"
  },
  {
    "location":"서울특별시 송파구 방이동",
    "title":"Bin29"
  },
  {
    "location":"서울특별시 송파구 오금동",
    "title":"브로버거"
  },
  {
    "location":"서울특별시 송파구 오금동",
    "title":"큐스시"
  },
  {
    "location":"서울특별시 송파구 오금동",
    "title":"이경진우렁쌈밥정식"
  },
  {
    "location":"서울특별시 송파구 오금동",
    "title":"춘향골남원추어탕"
  },
  {
    "location":"서울특별시 송파구 오금동",
    "title":"홍팥집"
  },
  {
    "location":"서울특별시 송파구 오금동",
    "title":"이낙근찹쌀떡베이커리"
  },
  {
    "location":"서울특별시 송파구 오금동",
    "title":"오발탄"
  },
  {
    "location":"서울특별시 송파구 오금동",
    "title":"프로퍼커피바"
  },
  {
    "location":"서울특별시 송파구 오금동",
    "title":"흥도식당"
  },
  {
    "location":"서울특별시 송파구 오금동",
    "title":"장털보설렁탕"
  },
  {
    "location":"서울특별시 송파구 오금동",
    "title":"꼬앙드파리"
  },
  {
    "location":"서울특별시 송파구 오금동",
    "title":"베네토"
  },
  {
    "location":"서울특별시 송파구 오금동",
    "title":"내꾸미쭈꾸미"
  },
  {
    "location":"서울특별시 송파구 오금동",
    "title":"봉평메밀나라"
  },
  {
    "location":"서울특별시 송파구 오금동",
    "title":"부산복집"
  },
  {
    "location":"서울특별시 송파구 오금동",
    "title":"등촌샤브칼국수"
  },
  {
    "location":"서울특별시 송파구 오금동",
    "title":"카페블라썸"
  },
  {
    "location":"서울특별시 송파구 오금동",
    "title":"라운징북스"
  },
  {
    "location":"서울특별시 송파구 오금동",
    "title":"남도마루"
  },
  {
    "location":"서울특별시 송파구 오금동",
    "title":"안동한우정육식당"
  },
  {
    "location":"서울특별시 송파구 오금동",
    "title":"이디야커피"
  },
  {
    "location":"서울특별시 송파구 오금동",
    "title":"옛날소머리국밥집"
  },
  {
    "location":"서울특별시 송파구 오금동",
    "title":"루시몽"
  },
  {
    "location":"서울특별시 송파구 오금동",
    "title":"채완"
  },
  {
    "location":"서울특별시 송파구 오금동",
    "title":"카페아이린"
  },
  {
    "location":"서울특별시 송파구 오금동",
    "title":"호치킨"
  },
  {
    "location":"서울특별시 송파구 오금동",
    "title":"안주마을"
  },
  {
    "location":"서울특별시 송파구 오금동",
    "title":"필커피"
  },
  {
    "location":"서울특별시 송파구 오금동",
    "title":"집밥 레몬트리"
  },
  {
    "location":"서울특별시 송파구 오금동",
    "title":"일구칠사"
  },
  {
    "location":"서울특별시 송파구 오금동",
    "title":"향호면옥"
  },
  {
    "location":"서울특별시 송파구 오금동",
    "title":"치킨갑"
  },
  {
    "location":"서울특별시 송파구 오금동",
    "title":"제주물담"
  },
  {
    "location":"서울특별시 송파구 오금동",
    "title":"도나도나"
  },
  {
    "location":"서울특별시 송파구 오금동",
    "title":"엘리스플레이스"
  },
  {
    "location":"서울특별시 송파구 오금동",
    "title":"프랭크서울"
  },
  {
    "location":"서울특별시 송파구 오금동",
    "title":"크럼버스"
  },
  {
    "location":"서울특별시 송파구 오금동",
    "title":"오도브"
  },
  {
    "location":"서울특별시 송파구 오금동",
    "title":"다래"
  },
  {
    "location":"서울특별시 송파구 오금동",
    "title":"솔레미오"
  },
  {
    "location":"서울특별시 송파구 오금동",
    "title":"4.5평우동집"
  },
  {
    "location":"서울특별시 송파구 오금동",
    "title":"다래연"
  },
  {
    "location":"서울특별시 송파구 오금동",
    "title":"촌돼지"
  },
  {
    "location":"서울특별시 송파구 오금동",
    "title":"꼼떼"
  },
  {
    "location":"서울특별시 송파구 오금동",
    "title":"머스타시로스터스"
  },
  {
    "location":"서울특별시 송파구 오금동",
    "title":"태양수제숯불갈비"
  },
  {
    "location":"서울특별시 송파구 오금동",
    "title":"밀크림"
  },
  {
    "location":"서울특별시 송파구 오금동",
    "title":"연형"
  },
  {
    "location":"서울특별시 송파구 오금동",
    "title":"신참떡볶이"
  },
  {
    "location":"서울특별시 송파구 오금동",
    "title":"마시리벌교참꼬막"
  },
  {
    "location":"서울특별시 송파구 오금동",
    "title":"케미"
  },
  {
    "location":"서울특별시 송파구 오금동",
    "title":"본향"
  },
  {
    "location":"서울특별시 송파구 오금동",
    "title":"동명원"
  },
  {
    "location":"서울특별시 송파구 오금동",
    "title":"기린차이나"
  },
  {
    "location":"서울특별시 송파구 오금동",
    "title":"왕스시"
  },
  {
    "location":"서울특별시 송파구 오금동",
    "title":"롤스시"
  },
  {
    "location":"서울특별시 송파구 오금동",
    "title":"가마솥감자탕"
  },
  {
    "location":"서울특별시 송파구 오금동",
    "title":"그레이에덴"
  },
  {
    "location":"서울특별시 송파구 오금동",
    "title":"군산집"
  },
  {
    "location":"서울특별시 송파구 오금동",
    "title":"밀향기해물손칼국수"
  },
  {
    "location":"서울특별시 송파구 오금동",
    "title":"송파샤브샤브칼국수"
  },
  {
    "location":"서울특별시 송파구 오금동",
    "title":"깐부치킨"
  },
  {
    "location":"서울특별시 송파구 오금동",
    "title":"도리네 한우곱창"
  },
  {
    "location":"서울특별시 송파구 오금동",
    "title":"썸씽에스프레소"
  },
  {
    "location":"서울특별시 송파구 오금동",
    "title":"봉평산골메밀촌"
  },
  {
    "location":"서울특별시 송파구 오금동",
    "title":"더남도의 향기"
  },
  {
    "location":"서울특별시 송파구 오금동",
    "title":"래향"
  },
  {
    "location":"서울특별시 송파구 오금동",
    "title":"명품한우정육식당"
  },
  {
    "location":"서울특별시 송파구 오금동",
    "title":"보배네집"
  },
  {
    "location":"서울특별시 송파구 오금동",
    "title":"갈비시대"
  },
  {
    "location":"서울특별시 송파구 오금동",
    "title":"루엔타이"
  },
  {
    "location":"서울특별시 송파구 오금동",
    "title":"프롬더빈"
  },
  {
    "location":"서울특별시 송파구 오금동",
    "title":"독천낙지골"
  },
  {
    "location":"서울특별시 송파구 오금동",
    "title":"사적인공간"
  },
  {
    "location":"서울특별시 송파구 오금동",
    "title":"행님아"
  },
  {
    "location":"서울특별시 송파구 오금동",
    "title":"신촌황소곱창"
  },
  {
    "location":"서울특별시 송파구 오금동",
    "title":"쏘아베"
  },
  {
    "location":"서울특별시 송파구 오금동",
    "title":"시즈너블베이커리"
  },
  {
    "location":"서울특별시 송파구 오금동",
    "title":"단백한하루"
  },
  {
    "location":"서울특별시 송파구 오금동",
    "title":"윤화돈까스"
  },
  {
    "location":"서울특별시 송파구 오금동",
    "title":"김밥마을"
  },
  {
    "location":"서울특별시 송파구 오금동",
    "title":"개성옥"
  },
  {
    "location":"서울특별시 송파구 오금동",
    "title":"가연전통비빔밥샤브칼국수"
  },
  {
    "location":"서울특별시 송파구 오금동",
    "title":"탐라꿀순이"
  },
  {
    "location":"서울특별시 송파구 오금동",
    "title":"썬파닭"
  },
  {
    "location":"서울특별시 송파구 오금동",
    "title":"다미소"
  },
  {
    "location":"서울특별시 송파구 오금동",
    "title":"화포식당"
  },
  {
    "location":"서울특별시 송파구 오금동",
    "title":"대밭골우렁쌈밥"
  },
  {
    "location":"서울특별시 송파구 오금동",
    "title":"옛날삼겹살5900"
  },
  {
    "location":"서울특별시 송파구 오금동",
    "title":"어구이"
  },
  {
    "location":"서울특별시 송파구 오금동",
    "title":"청백산농원가든"
  },
  {
    "location":"서울특별시 송파구 오금동",
    "title":"조선양평해장국"
  },
  {
    "location":"서울특별시 송파구 오금동",
    "title":"쌍대"
  },
  {
    "location":"서울특별시 송파구 오금동",
    "title":"오금동커피"
  },
  {
    "location":"서울특별시 송파구 오금동",
    "title":"아이엠쌈"
  },
  {
    "location":"서울특별시 송파구 오금동",
    "title":"기사식당"
  },
  {
    "location":"서울특별시 송파구 오금동",
    "title":"마시마니본사"
  },
  {
    "location":"서울특별시 송파구 오금동",
    "title":"명가마을"
  },
  {
    "location":"서울특별시 송파구 오금동",
    "title":"유채"
  },
  {
    "location":"서울특별시 송파구 오금동",
    "title":"토담"
  },
  {
    "location":"서울특별시 송파구 오금동",
    "title":"버드나무집"
  },
  {
    "location":"서울특별시 송파구 오금동",
    "title":"난향"
  },
  {
    "location":"서울특별시 송파구 오금동",
    "title":"피자나라치킨공주"
  },
  {
    "location":"서울특별시 송파구 오금동",
    "title":"만득이곱창"
  },
  {
    "location":"서울특별시 송파구 오금동",
    "title":"미님커피"
  },
  {
    "location":"서울특별시 송파구 오금동",
    "title":"더카페"
  },
  {
    "location":"서울특별시 송파구 오금동",
    "title":"오누이부대찌개"
  },
  {
    "location":"서울특별시 송파구 오금동",
    "title":"풍원"
  },
  {
    "location":"서울특별시 송파구 오금동",
    "title":"신의주찹쌀순대"
  },
  {
    "location":"서울특별시 송파구 오금동",
    "title":"감치래"
  },
  {
    "location":"서울특별시 송파구 오금동",
    "title":"빠띠시에"
  },
  {
    "location":"서울특별시 송파구 오금동",
    "title":"우돈골"
  },
  {
    "location":"서울특별시 송파구 오금동",
    "title":"진국시"
  },
  {
    "location":"서울특별시 송파구 오금동",
    "title":"커피벨라"
  },
  {
    "location":"서울특별시 송파구 오금동",
    "title":"맘마킹도시락올림픽공원"
  },
  {
    "location":"서울특별시 송파구 오금동",
    "title":"써클커피"
  },
  {
    "location":"서울특별시 송파구 오금동",
    "title":"고향산천"
  },
  {
    "location":"서울특별시 송파구 오금동",
    "title":"떡이랑한과랑"
  },
  {
    "location":"서울특별시 송파구 오금동",
    "title":"알앤비"
  },
  {
    "location":"서울특별시 송파구 오금동",
    "title":"토크쇼"
  },
  {
    "location":"서울특별시 송파구 오금동",
    "title":"양가"
  },
  {
    "location":"서울특별시 송파구 오금동",
    "title":"김밥천국"
  },
  {
    "location":"서울특별시 송파구 오금동",
    "title":"떡미당"
  },
  {
    "location":"서울특별시 송파구 오금동",
    "title":"전주콩나물국밥"
  },
  {
    "location":"서울특별시 송파구 오금동",
    "title":"카페이응"
  },
  {
    "location":"서울특별시 송파구 오금동",
    "title":"테피"
  },
  {
    "location":"서울특별시 송파구 오금동",
    "title":"그리드 카페"
  },
  {
    "location":"서울특별시 송파구 오금동",
    "title":"칡산에황제보쌈&곤드레돌솥밥옹심이칼국수"
  },
  {
    "location":"서울특별시 송파구 거여동",
    "title":"돈까스클럽"
  },
  {
    "location":"서울특별시 송파구 거여동",
    "title":"심마니백숙"
  },
  {
    "location":"서울특별시 송파구 거여동",
    "title":"투썸플레이스"
  },
  {
    "location":"서울특별시 송파구 거여동",
    "title":"이디야커피"
  },
  {
    "location":"서울특별시 송파구 거여동",
    "title":"양곱막"
  },
  {
    "location":"서울특별시 송파구 거여동",
    "title":"백가네감자탕"
  },
  {
    "location":"서울특별시 송파구 거여동",
    "title":"뮤지키사운드"
  },
  {
    "location":"서울특별시 송파구 거여동",
    "title":"김씨네명가국수앤불냉면"
  },
  {
    "location":"서울특별시 송파구 거여동",
    "title":"송치"
  },
  {
    "location":"서울특별시 송파구 거여동",
    "title":"해인김밥"
  },
  {
    "location":"서울특별시 송파구 거여동",
    "title":"은혜곱창"
  },
  {
    "location":"서울특별시 송파구 거여동",
    "title":"매드독스"
  },
  {
    "location":"서울특별시 송파구 거여동",
    "title":"어쭈구리"
  },
  {
    "location":"서울특별시 송파구 거여동",
    "title":"본죽"
  },
  {
    "location":"서울특별시 송파구 거여동",
    "title":"백두산"
  },
  {
    "location":"서울특별시 송파구 거여동",
    "title":"원할머니보쌈족발"
  },
  {
    "location":"서울특별시 송파구 거여동",
    "title":"돌담아구찜"
  },
  {
    "location":"서울특별시 송파구 거여동",
    "title":"배스킨라빈스"
  },
  {
    "location":"서울특별시 송파구 거여동",
    "title":"김리사철탕"
  },
  {
    "location":"서울특별시 송파구 거여동",
    "title":"동대문엽기떡볶이"
  },
  {
    "location":"서울특별시 송파구 거여동",
    "title":"명가정통수타중국요리점"
  },
  {
    "location":"서울특별시 송파구 거여동",
    "title":"궁전떡집"
  },
  {
    "location":"서울특별시 송파구 거여동",
    "title":"어굼터"
  },
  {
    "location":"서울특별시 송파구 거여동",
    "title":"김씨네돌솥밥순두부"
  },
  {
    "location":"서울특별시 송파구 거여동",
    "title":"남한산성"
  },
  {
    "location":"서울특별시 송파구 거여동",
    "title":"별미팥죽"
  },
  {
    "location":"서울특별시 송파구 거여동",
    "title":"카페고센"
  },
  {
    "location":"서울특별시 송파구 거여동",
    "title":"순자네식당"
  },
  {
    "location":"서울특별시 송파구 거여동",
    "title":"닭익는마을"
  },
  {
    "location":"서울특별시 송파구 거여동",
    "title":"피자마스터"
  },
  {
    "location":"서울특별시 송파구 거여동",
    "title":"썬파닭"
  },
  {
    "location":"서울특별시 송파구 거여동",
    "title":"장어전문점"
  },
  {
    "location":"서울특별시 송파구 거여동",
    "title":"동네형아"
  },
  {
    "location":"서울특별시 송파구 거여동",
    "title":"법성포굴비사랑"
  },
  {
    "location":"서울특별시 송파구 거여동",
    "title":"아재짜장"
  },
  {
    "location":"서울특별시 송파구 거여동",
    "title":"봉평형제메밀"
  },
  {
    "location":"서울특별시 송파구 거여동",
    "title":"옛맛참숯화로구이"
  },
  {
    "location":"서울특별시 송파구 거여동",
    "title":"원참치"
  },
  {
    "location":"서울특별시 송파구 거여동",
    "title":"해아랑"
  },
  {
    "location":"서울특별시 송파구 거여동",
    "title":"최대섭대박김밥"
  },
  {
    "location":"서울특별시 송파구 거여동",
    "title":"나레초밥"
  },
  {
    "location":"서울특별시 송파구 거여동",
    "title":"베트남쌀국수"
  },
  {
    "location":"서울특별시 송파구 거여동",
    "title":"동촌보리밥돈까스"
  },
  {
    "location":"서울특별시 송파구 거여동",
    "title":"부지깽이"
  },
  {
    "location":"서울특별시 송파구 거여동",
    "title":"하늘이네장칼국수"
  },
  {
    "location":"서울특별시 송파구 거여동",
    "title":"채선당"
  },
  {
    "location":"서울특별시 송파구 거여동",
    "title":"가야촌유황오리"
  },
  {
    "location":"서울특별시 송파구 거여동",
    "title":"한방통닭&바베큐"
  },
  {
    "location":"서울특별시 송파구 거여동",
    "title":"일심해장국"
  },
  {
    "location":"서울특별시 송파구 거여동",
    "title":"바다속안주"
  },
  {
    "location":"서울특별시 송파구 거여동",
    "title":"항아리보쌈"
  },
  {
    "location":"서울특별시 송파구 거여동",
    "title":"동방양꼬치"
  },
  {
    "location":"서울특별시 송파구 거여동",
    "title":"인키친"
  },
  {
    "location":"서울특별시 송파구 거여동",
    "title":"만선전어박사"
  },
  {
    "location":"서울특별시 송파구 거여동",
    "title":"싸다김밥"
  },
  {
    "location":"서울특별시 송파구 거여동",
    "title":"카페베네"
  },
  {
    "location":"서울특별시 송파구 거여동",
    "title":"광주생오리돌구이"
  },
  {
    "location":"서울특별시 송파구 거여동",
    "title":"젤리베리"
  },
  {
    "location":"서울특별시 송파구 거여동",
    "title":"서초갈비"
  },
  {
    "location":"서울특별시 송파구 거여동",
    "title":"차란"
  },
  {
    "location":"서울특별시 송파구 거여동",
    "title":"갈맛집"
  },
  {
    "location":"서울특별시 송파구 마천동",
    "title":"내일도 두부"
  },
  {
    "location":"서울특별시 송파구 마천동",
    "title":"커피가"
  },
  {
    "location":"서울특별시 송파구 마천동",
    "title":"이룸커피"
  },
  {
    "location":"서울특별시 송파구 마천동",
    "title":"도촌동태나라"
  },
  {
    "location":"서울특별시 송파구 마천동",
    "title":"장수왕족발"
  },
  {
    "location":"서울특별시 송파구 마천동",
    "title":"마천루"
  },
  {
    "location":"서울특별시 송파구 마천동",
    "title":"떡볶이나라"
  },
  {
    "location":"서울특별시 송파구 마천동",
    "title":"명동홍두깨손칼국수"
  },
  {
    "location":"서울특별시 송파구 마천동",
    "title":"수원집순대국"
  },
  {
    "location":"서울특별시 송파구 마천동",
    "title":"할매순대국"
  },
  {
    "location":"서울특별시 송파구 마천동",
    "title":"스타벅스"
  },
  {
    "location":"서울특별시 송파구 마천동",
    "title":"효동각"
  },
  {
    "location":"서울특별시 송파구 마천동",
    "title":"앵거스박고기공장"
  },
  {
    "location":"서울특별시 송파구 마천동",
    "title":"고기굽는마을"
  },
  {
    "location":"서울특별시 송파구 마천동",
    "title":"착한밥집"
  },
  {
    "location":"서울특별시 송파구 마천동",
    "title":"유천냉면"
  },
  {
    "location":"서울특별시 송파구 마천동",
    "title":"소육옥"
  },
  {
    "location":"서울특별시 송파구 마천동",
    "title":"종로떡집"
  },
  {
    "location":"서울특별시 송파구 마천동",
    "title":"피노키오생생돈까스"
  },
  {
    "location":"서울특별시 송파구 마천동",
    "title":"카페298"
  },
  {
    "location":"서울특별시 송파구 마천동",
    "title":"권순화보쌈족발"
  },
  {
    "location":"서울특별시 송파구 마천동",
    "title":"바니치킨"
  },
  {
    "location":"서울특별시 송파구 마천동",
    "title":"프라브"
  },
  {
    "location":"서울특별시 송파구 마천동",
    "title":"우돈가네맛구이"
  },
  {
    "location":"서울특별시 송파구 마천동",
    "title":"오꾸꼬"
  },
  {
    "location":"서울특별시 송파구 마천동",
    "title":"용문각"
  },
  {
    "location":"서울특별시 송파구 마천동",
    "title":"코바코"
  },
  {
    "location":"서울특별시 송파구 마천동",
    "title":"화평동왕냉면"
  },
  {
    "location":"서울특별시 송파구 마천동",
    "title":"버벅이네"
  },
  {
    "location":"서울특별시 송파구 마천동",
    "title":"도담정"
  },
  {
    "location":"서울특별시 송파구 마천동",
    "title":"행복을나누는사람들"
  },
  {
    "location":"서울특별시 송파구 마천동",
    "title":"이슬베이커리"
  },
  {
    "location":"서울특별시 송파구 마천동",
    "title":"대박"
  },
  {
    "location":"서울특별시 송파구 마천동",
    "title":"대구왕뽈떼기"
  },
  {
    "location":"서울특별시 송파구 마천동",
    "title":"장원보쌈"
  },
  {
    "location":"서울특별시 송파구 마천동",
    "title":"섬진강민물장어"
  },
  {
    "location":"서울특별시 송파구 마천동",
    "title":"외로워도술퍼드"
  },
  {
    "location":"서울특별시 송파구 마천동",
    "title":"떡마을한과"
  },
  {
    "location":"서울특별시 송파구 마천동",
    "title":"병천가마솥토종순대"
  },
  {
    "location":"서울특별시 송파구 마천동",
    "title":"주원산유황오리"
  },
  {
    "location":"서울특별시 송파구 마천동",
    "title":"감미식당"
  },
  {
    "location":"서울특별시 송파구 마천동",
    "title":"일도불백"
  },
  {
    "location":"서울특별시 송파구 마천동",
    "title":"하나로황제짜장"
  },
  {
    "location":"서울특별시 송파구 마천동",
    "title":"수타손짜장마을"
  },
  {
    "location":"서울특별시 송파구 마천동",
    "title":"마포숯불갈비"
  },
  {
    "location":"서울특별시 송파구 마천동",
    "title":"김밥나라"
  },
  {
    "location":"서울특별시 송파구 마천동",
    "title":"최가네막국수순대국"
  },
  {
    "location":"서울특별시 송파구 마천동",
    "title":"마천면가"
  },
  {
    "location":"서울특별시 송파구 마천동",
    "title":"원이네순대국"
  },
  {
    "location":"서울특별시 송파구 마천동",
    "title":"참새방앗간포장마차"
  },
  {
    "location":"서울특별시 송파구 마천동",
    "title":"뽀빠이냉면"
  },
  {
    "location":"서울특별시 송파구 마천동",
    "title":"카페 그린스"
  },
  {
    "location":"서울특별시 송파구 마천동",
    "title":"마천국수김밥"
  },
  {
    "location":"서울특별시 송파구 마천동",
    "title":"치킨하나"
  },
  {
    "location":"서울특별시 송파구 마천동",
    "title":"진미곱창"
  },
  {
    "location":"서울특별시 송파구 마천동",
    "title":"홍조"
  },
  {
    "location":"서울특별시 송파구 마천동",
    "title":"언짠네"
  },
  {
    "location":"서울특별시 송파구 마천동",
    "title":"마천가마솥설렁탕"
  },
  {
    "location":"서울특별시 송파구 마천동",
    "title":"영광사철탕"
  },
  {
    "location":"서울특별시 송파구 마천동",
    "title":"다래홍두깨손칼국수"
  },
  {
    "location":"서울특별시 송파구 마천동",
    "title":"청해루"
  },
  {
    "location":"서울특별시 송파구 마천동",
    "title":"남한산성"
  },
  {
    "location":"서울특별시 송파구 마천동",
    "title":"소문난대박집"
  },
  {
    "location":"서울특별시 송파구 마천동",
    "title":"교동짬뽕"
  },
  {
    "location":"서울특별시 송파구 마천동",
    "title":"신흥토종한우"
  },
  {
    "location":"서울특별시 송파구 마천동",
    "title":"우전축산정육식당"
  },
  {
    "location":"서울특별시 송파구 마천동",
    "title":"제주목장"
  },
  {
    "location":"서울특별시 송파구 마천동",
    "title":"장가네식당"
  },
  {
    "location":"서울특별시 송파구 마천동",
    "title":"공릉동원조멸치국수"
  },
  {
    "location":"서울특별시 송파구 마천동",
    "title":"청년다방"
  },
  {
    "location":"서울특별시 송파구 마천동",
    "title":"통발집"
  },
  {
    "location":"서울특별시 송파구 마천동",
    "title":"소문난곱창"
  },
  {
    "location":"서울특별시 송파구 마천동",
    "title":"대평족발"
  },
  {
    "location":"서울특별시 송파구 마천동",
    "title":"잔치국수"
  },
  {
    "location":"서울특별시 송파구 마천동",
    "title":"벧엘칼국수"
  },
  {
    "location":"서울특별시 송파구 마천동",
    "title":"시장통횟집"
  },
  {
    "location":"서울특별시 송파구 마천동",
    "title":"장충동한방족발"
  },
  {
    "location":"서울특별시 송파구 마천동",
    "title":"맛나닭가마솥치킨"
  },
  {
    "location":"서울특별시 송파구 마천동",
    "title":"차박사얼큰이"
  },
  {
    "location":"서울특별시 송파구 마천동",
    "title":"유가네한우소머리곰탕"
  },
  {
    "location":"서울특별시 송파구 마천동",
    "title":"만리궁"
  },
  {
    "location":"서울특별시 송파구 마천동",
    "title":"뽈떼기"
  },
  {
    "location":"서울특별시 송파구 마천동",
    "title":"대장갈매기"
  },
  {
    "location":"서울특별시 송파구 마천동",
    "title":"쪼끼광장"
  },
  {
    "location":"서울특별시 송파구 마천동",
    "title":"명승가든"
  },
  {
    "location":"서울특별시 송파구 마천동",
    "title":"통통만두"
  },
  {
    "location":"서울특별시 송파구 마천동",
    "title":"참숯골"
  },
  {
    "location":"서울특별시 송파구 마천동",
    "title":"장원족발"
  },
  {
    "location":"서울특별시 송파구 마천동",
    "title":"꾸어구어"
  },
  {
    "location":"서울특별시 송파구 마천동",
    "title":"풍성식당"
  },
  {
    "location":"서울특별시 송파구 마천동",
    "title":"종로회집"
  },
  {
    "location":"서울특별시 송파구 마천동",
    "title":"커피콩"
  },
  {
    "location":"서울특별시 송파구 마천동",
    "title":"프라이드데이"
  },
  {
    "location":"서울특별시 송파구 마천동",
    "title":"행님아"
  },
  {
    "location":"서울특별시 송파구 마천동",
    "title":"가야밀면"
  },
  {
    "location":"서울특별시 송파구 마천동",
    "title":"대삼반점"
  },
  {
    "location":"서울특별시 송파구 마천동",
    "title":"부어치킨"
  },
  {
    "location":"서울특별시 송파구 마천동",
    "title":"사카"
  },
  {
    "location":"서울특별시 송파구 마천동",
    "title":"고향떡집"
  },
  {
    "location":"서울특별시 송파구 마천동",
    "title":"웅스트릿"
  },
  {
    "location":"서울특별시 송파구 마천동",
    "title":"먹자곱창닭발"
  },
  {
    "location":"서울특별시 송파구 마천동",
    "title":"우리떡집"
  },
  {
    "location":"서울특별시 송파구 마천동",
    "title":"가얏골맛감자탕"
  },
  {
    "location":"서울특별시 송파구 마천동",
    "title":"소바향"
  },
  {
    "location":"서울특별시 송파구 마천동",
    "title":"옛날시골통닭"
  },
  {
    "location":"서울특별시 송파구 마천동",
    "title":"고계바"
  },
  {
    "location":"서울특별시 강동구 명일동",
    "title":"한방누룽지통닭"
  },
  {
    "location":"서울특별시 강동구 명일동",
    "title":"샬롬커피"
  },
  {
    "location":"서울특별시 강동구 명일동",
    "title":"봉트랩"
  },
  {
    "location":"서울특별시 강동구 명일동",
    "title":"에꼴드쉐프"
  },
  {
    "location":"서울특별시 강동구 명일동",
    "title":"4TENTIAL"
  },
  {
    "location":"서울특별시 강동구 명일동",
    "title":"운 삐아또"
  },
  {
    "location":"서울특별시 강동구 명일동",
    "title":"설빙"
  },
  {
    "location":"서울특별시 강동구 명일동",
    "title":"블랑디저트카페"
  },
  {
    "location":"서울특별시 강동구 명일동",
    "title":"롤앤스시"
  },
  {
    "location":"서울특별시 강동구 명일동",
    "title":"카페씨모"
  },
  {
    "location":"서울특별시 강동구 명일동",
    "title":"마포갈비"
  },
  {
    "location":"서울특별시 강동구 명일동",
    "title":"브레드앤밀"
  },
  {
    "location":"서울특별시 강동구 명일동",
    "title":"스키마야"
  },
  {
    "location":"서울특별시 강동구 명일동",
    "title":"화포식당"
  },
  {
    "location":"서울특별시 강동구 명일동",
    "title":"Cafe79 Page"
  },
  {
    "location":"서울특별시 강동구 명일동",
    "title":"갸또마마"
  },
  {
    "location":"서울특별시 강동구 명일동",
    "title":"까페파이나무"
  },
  {
    "location":"서울특별시 강동구 명일동",
    "title":"Mul Bar"
  },
  {
    "location":"서울특별시 강동구 명일동",
    "title":"까사데카페"
  },
  {
    "location":"서울특별시 강동구 명일동",
    "title":"명가돈가스"
  },
  {
    "location":"서울특별시 강동구 명일동",
    "title":"테마라면"
  },
  {
    "location":"서울특별시 강동구 명일동",
    "title":"컨테인커피"
  },
  {
    "location":"서울특별시 강동구 명일동",
    "title":"아름다운제주돈"
  },
  {
    "location":"서울특별시 강동구 명일동",
    "title":"토닥토닥"
  },
  {
    "location":"서울특별시 강동구 명일동",
    "title":"스시키라"
  },
  {
    "location":"서울특별시 강동구 명일동",
    "title":"수작"
  },
  {
    "location":"서울특별시 강동구 명일동",
    "title":"소양골춘천닭갈비막국수"
  },
  {
    "location":"서울특별시 강동구 명일동",
    "title":"왕십리왕곱창"
  },
  {
    "location":"서울특별시 강동구 명일동",
    "title":"명일샤브샤브칼국수"
  },
  {
    "location":"서울특별시 강동구 명일동",
    "title":"쿠스돈까스"
  },
  {
    "location":"서울특별시 강동구 명일동",
    "title":"베이커리휴고"
  },
  {
    "location":"서울특별시 강동구 명일동",
    "title":"유천냉면"
  },
  {
    "location":"서울특별시 강동구 명일동",
    "title":"산골닭갈비"
  },
  {
    "location":"서울특별시 강동구 명일동",
    "title":"김가네"
  },
  {
    "location":"서울특별시 강동구 명일동",
    "title":"산수고원"
  },
  {
    "location":"서울특별시 강동구 명일동",
    "title":"욜로"
  },
  {
    "location":"서울특별시 강동구 명일동",
    "title":"마노아"
  },
  {
    "location":"서울특별시 강동구 명일동",
    "title":"삼대냉면"
  },
  {
    "location":"서울특별시 강동구 명일동",
    "title":"우자매"
  },
  {
    "location":"서울특별시 강동구 명일동",
    "title":"림"
  },
  {
    "location":"서울특별시 강동구 명일동",
    "title":"포메인"
  },
  {
    "location":"서울특별시 강동구 명일동",
    "title":"꿀닭"
  },
  {
    "location":"서울특별시 강동구 명일동",
    "title":"옛날손짜장"
  },
  {
    "location":"서울특별시 강동구 명일동",
    "title":"만석바지락칼국수"
  },
  {
    "location":"서울특별시 강동구 명일동",
    "title":"본가삼대냉면"
  },
  {
    "location":"서울특별시 강동구 명일동",
    "title":"카페비"
  },
  {
    "location":"서울특별시 강동구 명일동",
    "title":"도도참치"
  },
  {
    "location":"서울특별시 강동구 명일동",
    "title":"스카이호프"
  },
  {
    "location":"서울특별시 강동구 명일동",
    "title":"마노스커피"
  },
  {
    "location":"서울특별시 강동구 명일동",
    "title":"바른맥주"
  },
  {
    "location":"서울특별시 강동구 명일동",
    "title":"고향집손칼국수"
  },
  {
    "location":"서울특별시 강동구 명일동",
    "title":"한스"
  },
  {
    "location":"서울특별시 강동구 명일동",
    "title":"가마골"
  },
  {
    "location":"서울특별시 강동구 명일동",
    "title":"모이카롱"
  },
  {
    "location":"서울특별시 강동구 명일동",
    "title":"생활맥주"
  },
  {
    "location":"서울특별시 강동구 명일동",
    "title":"삼끼막창"
  },
  {
    "location":"서울특별시 강동구 명일동",
    "title":"2 ROUND"
  },
  {
    "location":"서울특별시 강동구 명일동",
    "title":"맘스터치"
  },
  {
    "location":"서울특별시 강동구 명일동",
    "title":"굴한마당"
  },
  {
    "location":"서울특별시 강동구 명일동",
    "title":"다락"
  },
  {
    "location":"서울특별시 강동구 명일동",
    "title":"황푸차이나"
  },
  {
    "location":"서울특별시 강동구 명일동",
    "title":"앙상블"
  },
  {
    "location":"서울특별시 강동구 명일동",
    "title":"빠네렌토"
  },
  {
    "location":"서울특별시 강동구 명일동",
    "title":"캄포"
  },
  {
    "location":"서울특별시 강동구 명일동",
    "title":"진이네떡볶이"
  },
  {
    "location":"서울특별시 강동구 명일동",
    "title":"스윗솔트"
  },
  {
    "location":"서울특별시 강동구 명일동",
    "title":"명일원조닭발"
  },
  {
    "location":"서울특별시 강동구 명일동",
    "title":"꾸러기분식"
  },
  {
    "location":"서울특별시 강동구 명일동",
    "title":"로겐하임"
  },
  {
    "location":"서울특별시 강동구 명일동",
    "title":"시찌린"
  },
  {
    "location":"서울특별시 강동구 명일동",
    "title":"숟가락반상 마실"
  },
  {
    "location":"서울특별시 강동구 명일동",
    "title":"카페수요일"
  },
  {
    "location":"서울특별시 강동구 명일동",
    "title":"스시혼"
  },
  {
    "location":"서울특별시 강동구 명일동",
    "title":"등촌샤브칼국수"
  },
  {
    "location":"서울특별시 강동구 명일동",
    "title":"라베이크"
  },
  {
    "location":"서울특별시 강동구 명일동",
    "title":"엔메르"
  },
  {
    "location":"서울특별시 강동구 명일동",
    "title":"메콩타이"
  },
  {
    "location":"서울특별시 강동구 명일동",
    "title":"원조쌈밥집"
  },
  {
    "location":"서울특별시 강동구 명일동",
    "title":"원조숯불쭈꾸미"
  },
  {
    "location":"서울특별시 강동구 명일동",
    "title":"깐부치킨"
  },
  {
    "location":"서울특별시 강동구 명일동",
    "title":"홍짜장"
  },
  {
    "location":"서울특별시 강동구 명일동",
    "title":"봉구스밥버거"
  },
  {
    "location":"서울특별시 강동구 명일동",
    "title":"낸시스"
  },
  {
    "location":"서울특별시 강동구 명일동",
    "title":"숯불돼지갈비마포집"
  },
  {
    "location":"서울특별시 강동구 명일동",
    "title":"놀부부대찌개&철판구이"
  },
  {
    "location":"서울특별시 강동구 명일동",
    "title":"숯불직화꼬치구이"
  },
  {
    "location":"서울특별시 강동구 명일동",
    "title":"매일구움"
  },
  {
    "location":"서울특별시 강동구 명일동",
    "title":"카페오메가"
  },
  {
    "location":"서울특별시 강동구 명일동",
    "title":"와사비"
  },
  {
    "location":"서울특별시 강동구 명일동",
    "title":"스시훈"
  },
  {
    "location":"서울특별시 강동구 명일동",
    "title":"농협안심한우"
  },
  {
    "location":"서울특별시 강동구 명일동",
    "title":"캐서린다이너"
  },
  {
    "location":"서울특별시 강동구 명일동",
    "title":"동그림"
  },
  {
    "location":"서울특별시 강동구 명일동",
    "title":"베트남노상식당"
  },
  {
    "location":"서울특별시 강동구 명일동",
    "title":"명일곱창"
  },
  {
    "location":"서울특별시 강동구 명일동",
    "title":"토론토"
  },
  {
    "location":"서울특별시 강동구 명일동",
    "title":"홀릭커피"
  },
  {
    "location":"서울특별시 강동구 명일동",
    "title":"카페인"
  },
  {
    "location":"서울특별시 강동구 명일동",
    "title":"아빠가만든스파게티"
  },
  {
    "location":"서울특별시 강동구 명일동",
    "title":"닐리"
  },
  {
    "location":"서울특별시 강동구 명일동",
    "title":"천호동원조춘천족발집"
  },
  {
    "location":"서울특별시 강동구 명일동",
    "title":"동대문엽기떡볶이"
  },
  {
    "location":"서울특별시 강동구 명일동",
    "title":"이모네왕냉면"
  },
  {
    "location":"서울특별시 강동구 명일동",
    "title":"치어스"
  },
  {
    "location":"서울특별시 강동구 명일동",
    "title":"부산진오뎅"
  },
  {
    "location":"서울특별시 강동구 명일동",
    "title":"하남돼지집"
  },
  {
    "location":"서울특별시 강동구 명일동",
    "title":"지도리치킨"
  },
  {
    "location":"서울특별시 강동구 명일동",
    "title":"59쌀피자"
  },
  {
    "location":"서울특별시 강동구 명일동",
    "title":"한방삼계탕"
  },
  {
    "location":"서울특별시 강동구 명일동",
    "title":"송가네"
  },
  {
    "location":"서울특별시 강동구 명일동",
    "title":"스카이마늘치킨"
  },
  {
    "location":"서울특별시 강동구 명일동",
    "title":"가이토"
  },
  {
    "location":"서울특별시 강동구 명일동",
    "title":"맛닭꼬"
  },
  {
    "location":"서울특별시 강동구 명일동",
    "title":"어쭈꾸미"
  },
  {
    "location":"서울특별시 강동구 명일동",
    "title":"미성양꼬치"
  },
  {
    "location":"서울특별시 강동구 명일동",
    "title":"본죽앤비빔밥카페"
  },
  {
    "location":"서울특별시 강동구 명일동",
    "title":"미스터피자"
  },
  {
    "location":"서울특별시 강동구 명일동",
    "title":"한스델리"
  },
  {
    "location":"서울특별시 강동구 명일동",
    "title":"빽다방"
  },
  {
    "location":"서울특별시 강동구 명일동",
    "title":"광릉불고기"
  },
  {
    "location":"서울특별시 강동구 명일동",
    "title":"오븐마루"
  },
  {
    "location":"서울특별시 강동구 명일동",
    "title":"영덕물회"
  },
  {
    "location":"서울특별시 강동구 명일동",
    "title":"뮬바"
  },
  {
    "location":"서울특별시 강동구 명일동",
    "title":"놀부옛날통닭"
  },
  {
    "location":"서울특별시 강동구 명일동",
    "title":"도요청담꼬치"
  },
  {
    "location":"서울특별시 강동구 명일동",
    "title":"매콤촌"
  },
  {
    "location":"서울특별시 강동구 명일동",
    "title":"본죽"
  },
  {
    "location":"서울특별시 강동구 명일동",
    "title":"마루"
  },
  {
    "location":"서울특별시 강동구 명일동",
    "title":"플젠"
  },
  {
    "location":"서울특별시 강동구 명일동",
    "title":"남원골추어탕"
  },
  {
    "location":"서울특별시 강동구 명일동",
    "title":"소리꼴"
  },
  {
    "location":"서울특별시 강동구 명일동",
    "title":"파다닭"
  },
  {
    "location":"서울특별시 강동구 명일동",
    "title":"카모메심야식당"
  },
  {
    "location":"서울특별시 강동구 명일동",
    "title":"강동베이커리"
  },
  {
    "location":"서울특별시 강동구 명일동",
    "title":"안심정육식당"
  },
  {
    "location":"서울특별시 강동구 명일동",
    "title":"소소로운"
  },
  {
    "location":"서울특별시 강동구 명일동",
    "title":"미소야"
  },
  {
    "location":"서울특별시 강동구 명일동",
    "title":"훈훈한닭한마리"
  },
  {
    "location":"서울특별시 강동구 명일동",
    "title":"미각양꼬치"
  },
  {
    "location":"서울특별시 강동구 명일동",
    "title":"왕여사의왕맛있는집"
  },
  {
    "location":"서울특별시 강동구 명일동",
    "title":"장안면옥"
  },
  {
    "location":"서울특별시 강동구 명일동",
    "title":"몽키팡팡키즈카페"
  },
  {
    "location":"서울특별시 강동구 명일동",
    "title":"원점보쌈족발"
  },
  {
    "location":"서울특별시 강동구 명일동",
    "title":"북경반점"
  }
]